hereus_ui_3_2/__init__.py
hereus_ui_3_2/palette.py
hereus_ui_3_2-3.2.0.dist-info/LICENSE
hereus_ui_3_2-3.2.0.dist-info/METADATA
hereus_ui_3_2-3.2.0.dist-info/WHEEL
hereus_ui_3_2-3.2.0.dist-info/top_level.txt
hereus_ui_3_2-3.2.0.dist-info/RECORD
