Metadata-Version: 2.1
Name: hereus_ui_3_2
Version: 3.2.0
Summary: HereUS UI 3.2 for BevyFrame
License: Creative Commons Attribution ShareAlike 4.0
Project-URL: Homepage, https://ui.hereus.net/
Requires-Python: >=3.9
License-File: LICENSE
